packagedestination/__init__.py
packagedestiationnnnn-0.0.1.dist-info/METADATA
packagedestiationnnnn-0.0.1.dist-info/WHEEL
packagedestiationnnnn-0.0.1.dist-info/top_level.txt
packagedestiationnnnn-0.0.1.dist-info/RECORD
