Metadata-Version: 2.1
Name: packagedestiationnnnn
Version: 0.0.1
Summary: This is code with harry package
Home-page: UNKNOWN
Author: Harry
Author-email: UNKNOWN
License: UNKNOWN
Platform: UNKNOWN
